enimie/__init__.py
enimie/__main__.py
enimie-1.1.1.dist-info/METADATA
enimie-1.1.1.dist-info/WHEEL
enimie-1.1.1.dist-info/entry_points.txt
enimie-1.1.1.dist-info/top_level.txt
enimie-1.1.1.dist-info/RECORD
