Metadata-Version: 2.1
Name: enimie
Version: 1.1.1
Summary: It for wordlist attacks
Home-page: https://github.com/kavindunimesh/enimie
Author: kavindu nimesh
Author-email: k.nimesh.kn@gmail.com
License: MIT
Platform: UNKNOWN
Classifier: License :: OSI Approved :: MIT License
Classifier: Programming Language :: Python :: 3.6
Classifier: Programming Language :: Python :: 3.7
Classifier: Programming Language :: Python :: 3.8
Requires-Dist: requests
Requires-Dist: argparse
